NyxianXD/__init__.py
NyxianXD/api.py
NyxianXD/client.py
NyxianXD-1.0.2.dist-info/LICENSE
NyxianXD-1.0.2.dist-info/METADATA
NyxianXD-1.0.2.dist-info/WHEEL
NyxianXD-1.0.2.dist-info/top_level.txt
NyxianXD-1.0.2.dist-info/RECORD
