Metadata-Version: 2.1
Name: NyxianXD
Version: 1.0.2
Summary: Library Python untuk uploader Nyxian Network.
Home-page: https://github.com/nyxiancode
Author: Katsu
Author-email: support@nyxiannetwork.web.id
Classifier: Programming Language :: Python :: 3
Classifier: License :: OSI Approved :: MIT License
Classifier: Operating System :: OS Independent
Requires-Python: >=3.6
License-File: LICENSE
Requires-Dist: requests
